instachatbot/__init__.py
instachatbot/bot.py
instachatbot/nodes.py
instachatbot/state.py
instachatbot/storage.py
instachatbot-0.4.dist-info/LICENSE
instachatbot-0.4.dist-info/METADATA
instachatbot-0.4.dist-info/WHEEL
instachatbot-0.4.dist-info/top_level.txt
instachatbot-0.4.dist-info/RECORD
