Metadata-Version: 2.1
Name: instachatbot
Version: 0.4
Summary: Simple framework for building Instagram chat bots with menu driven interface
Home-page: https://github.com/art-vasilyev/instachatbot
Author: Artem Vasilyev
Author-email: artem.v.vasilyev@gmail.com
License: MIT
Keywords: chatbot,instagram
Platform: any
Requires-Python: >=3.6
Requires-Dist: instabot (>=0.78)
